fac_format/__init__.py
fac_format/parser.py
fac_format-0.1.2.dist-info/METADATA
fac_format-0.1.2.dist-info/WHEEL
fac_format-0.1.2.dist-info/licenses/LICENSE
fac_format-0.1.2.dist-info/RECORD
