Metadata-Version: 2.4
Name: fac-format
Version: 0.1.2
Summary: A deliberately complicated and inefficient file format alternative to JSON
Project-URL: Homepage, https://replit.com/@replit/fac-format
Project-URL: Bug Tracker, https://replit.com/@replit/fac-format/issues
Author: FAC Format Developers
License-File: LICENSE
Classifier: Development Status :: 3 - Alpha
Classifier: Intended Audience :: Developers
Classifier: License :: OSI Approved :: MIT License
Classifier: Operating System :: OS Independent
Classifier: Programming Language :: Python :: 3
Classifier: Topic :: File Formats
Classifier: Topic :: Software Development :: Libraries :: Python Modules
Requires-Python: >=3.7
